CODE_OF_CONDUCT.md
LICENSE
README.md
setup.py
.github/ISSUE_TEMPLATE/bug_report.md
.github/ISSUE_TEMPLATE/feature_request.md
examples/test1.py
examples/test2.ipynb
examples/test2.py
examples/test3.py
examples/test4.py
examples/test5.py
examples/data/1-1.txt
examples/data/1-2.txt
examples/data/1-3.txt
examples/data/1-4.txt
examples/data/1-5.txt
examples/data/2-1.txt
examples/data/2-2.txt
examples/data/2-3.txt
examples/data/2-4.txt
examples/data/2-5.txt
examples/data/3-1.txt
examples/data/3-2.txt
examples/data/3-3.txt
examples/data/3-4.txt
examples/data/3-5.txt
examples/data/5D.txt
examples/data/Example2.txt
figures/pyZiagn.png
figures/pyZiagn.svg
pyZiagn/__init__.py
pyZiagn/ziagn.py
pyZiagn.egg-info/PKG-INFO
pyZiagn.egg-info/SOURCES.txt
pyZiagn.egg-info/dependency_links.txt
pyZiagn.egg-info/requires.txt
pyZiagn.egg-info/top_level.txt
test/test.py