Metadata-Version: 2.1
Name: pyZiagn
Version: 0.1.6
Summary: Python librarY for material characteriZation based on experImental dAta for lightweiGht desigN
Home-page: https://github.com/e-dub/pyZiagn
Author: E. J. Wehrle
License: gpl-3.0
Platform: UNKNOWN
License-File: LICENSE
